x1/__init__.py
x1_icl-0.0.1.dist-info/LICENSE
x1_icl-0.0.1.dist-info/METADATA
x1_icl-0.0.1.dist-info/WHEEL
x1_icl-0.0.1.dist-info/top_level.txt
x1_icl-0.0.1.dist-info/RECORD
