Metadata-Version: 2.1
Name: x1-icl
Version: 0.0.1
Summary: API driven Machine Learning suite
Author-email: Areg Melik-Adamyan <areg.melikadamyan@gmail.com>, Pavel Chekin <pbchekin@gmail.com>
License: Apache License
Requires-Python: >=3.8
License-File: LICENSE
Requires-Dist: click
Provides-Extra: build
Requires-Dist: build ; extra == 'build'
Requires-Dist: twine ; extra == 'build'
Provides-Extra: test
Requires-Dist: botocore-stubs ; extra == 'test'
Requires-Dist: boto3-stubs[ec2] ; extra == 'test'
Requires-Dist: build ; extra == 'test'
Requires-Dist: mypy ; extra == 'test'
Requires-Dist: pytest ; extra == 'test'
Requires-Dist: pytest-asyncio ; extra == 'test'
Requires-Dist: pre-commit ; extra == 'test'
Requires-Dist: coverage ; extra == 'test'
